{
  "id": "acura-ilx-2023-le",
  "manufacturer": "Acura",
  "model": "ILX",
  "year": 2023,
  "trim": "LE",
  "testDate": "2024-01-23",
  "ratings": {
    "adult": 4.5,
    "child": 5,
    "pedestrian": 4,
    "safetyAssist": 4.5,
    "overall": 4.5
  },
  "crashTests": [
    {
      "type": "whiplash",
      "score": 12.7,
      "maxScore": 16,
      "description": "Excellent structural integrity maintained",
      "images": [
        "http://localhost:3000/img/3D-Car-Sample.jpg",
        "http://localhost:3000/img/3D-Car-Sample.jpg"
      ]
    },
    {
      "type": "pole",
      "score": 13,
      "maxScore": 16,
      "description": "Satisfactory protection for occupants",
      "images": [
        "http://localhost:3000/img/3D-Car-Sample.jpg",
        "http://localhost:3000/img/3D-Car-Sample.jpg"
      ]
    }
  ],
  "safetyFeatures": [
    {
      "name": "Anti-lock Braking System",
      "available": true,
      "standard": false,
      "performance": "Good"
    },
    {
      "name": "Lane Keep Assist",
      "available": true,
      "standard": true,
      "performance": "Adequate"
    },
    {
      "name": "Pedestrian Detection",
      "available": true,
      "standard": true,
      "performance": "Adequate"
    },
    {
      "name": "Traction Control",
      "available": false,
      "standard": false
    },
    {
      "name": "Electronic Stability Control",
      "available": true,
      "standard": false,
      "performance": "Good"
    },
    {
      "name": "Automatic High Beams",
      "available": true,
      "standard": false,
      "performance": "Adequate"
    },
    {
      "name": "Autonomous Emergency Braking",
      "available": true,
      "standard": false,
      "performance": "Fair"
    },
    {
      "name": "Lane Departure Warning",
      "available": true,
      "standard": false,
      "performance": "Excellent"
    },
    {
      "name": "Adaptive Cruise Control",
      "available": true,
      "standard": true,
      "performance": "Fair"
    },
    {
      "name": "Rear Cross Traffic Alert",
      "available": false,
      "standard": false
    },
    {
      "name": "Traffic Sign Recognition",
      "available": true,
      "standard": false,
      "performance": "Excellent"
    },
    {
      "name": "Forward Collision Warning",
      "available": true,
      "standard": true,
      "performance": "Fair"
    },
    {
      "name": "Blind Spot Monitoring",
      "available": true,
      "standard": true,
      "performance": "Fair"
    }
  ],
  "adultOccupant": {
    "score": 34.9,
    "maxScore": 38,
    "details": "The vehicle demonstrated strong performance in protecting adult occupants. Protection levels were good for all critical body areas."
  },
  "childOccupant": {
    "score": 48.4,
    "maxScore": 49,
    "details": "Child restraint systems were well accommodated. The vehicle provided good protection for child occupants of various sizes."
  },
  "vulnerableRoadUsers": {
    "score": 35.5,
    "maxScore": 42,
    "details": "The vehicle demonstrated strong pedestrian protection. Active safety systems performed well in avoiding vulnerable road user impacts."
  },
  "safetyAssist": {
    "score": 12.4,
    "maxScore": 14,
    "details": "Advanced driver assistance features are standard. All systems tested demonstrated good performance and reliability."
  },
  "images": {
    "main": "http://localhost:3000/img/3D-Car-Sample.jpg",
    "gallery": [
      "http://localhost:3000/img/3D-Car-Sample.jpg",
      "http://localhost:3000/img/3D-Car-Sample.jpg",
      "http://localhost:3000/img/3D-Car-Sample.jpg"
    ]
  },
  "videoUrl": "",
  "additionalNotes": "This vehicle demonstrates excellent overall safety performance with outstanding scores across all categories."
}